{"frames": {

"EscherStar3D.0001.png":
{
	"frame": {"x":462,"y":892,"w":462,"h":446},
	"rotated": false,
	"trimmed": true,
	"spriteSourceSize": {"x":380,"y":104,"w":462,"h":446},
	"sourceSize": {"w":1200,"h":675}
},
"EscherStar3D.0003.png":
{
	"frame": {"x":0,"y":2680,"w":462,"h":446},
	"rotated": false,
	"trimmed": true,
	"spriteSourceSize": {"x":380,"y":104,"w":462,"h":446},
	"sourceSize": {"w":1200,"h":675}
},
"EscherStar3D.0004.png":
{
	"frame": {"x":0,"y":0,"w":463,"h":446},
	"rotated": false,
	"trimmed": true,
	"spriteSourceSize": {"x":379,"y":104,"w":463,"h":446},
	"sourceSize": {"w":1200,"h":675}
},
"EscherStar3D.0005.png":
{
	"frame": {"x":0,"y":446,"w":463,"h":446},
	"rotated": false,
	"trimmed": true,
	"spriteSourceSize": {"x":378,"y":104,"w":463,"h":446},
	"sourceSize": {"w":1200,"h":675}
},
"EscherStar3D.0006.png":
{
	"frame": {"x":463,"y":0,"w":463,"h":446},
	"rotated": false,
	"trimmed": true,
	"spriteSourceSize": {"x":378,"y":104,"w":463,"h":446},
	"sourceSize": {"w":1200,"h":675}
},
"EscherStar3D.0007.png":
{
	"frame": {"x":926,"y":446,"w":462,"h":446},
	"rotated": false,
	"trimmed": true,
	"spriteSourceSize": {"x":378,"y":104,"w":462,"h":446},
	"sourceSize": {"w":1200,"h":675}
},
"EscherStar3D.0008.png":
{
	"frame": {"x":462,"y":1785,"w":460,"h":447},
	"rotated": false,
	"trimmed": true,
	"spriteSourceSize": {"x":378,"y":104,"w":460,"h":447},
	"sourceSize": {"w":1200,"h":675}
},
"EscherStar3D.0009.png":
{
	"frame": {"x":1380,"y":1785,"w":456,"h":447},
	"rotated": false,
	"trimmed": true,
	"spriteSourceSize": {"x":379,"y":104,"w":456,"h":447},
	"sourceSize": {"w":1200,"h":675}
},
"EscherStar3D.0010.png":
{
	"frame": {"x":1373,"y":2680,"w":450,"h":448},
	"rotated": false,
	"trimmed": true,
	"spriteSourceSize": {"x":381,"y":104,"w":450,"h":448},
	"sourceSize": {"w":1200,"h":675}
},
"EscherStar3D.0011.png":
{
	"frame": {"x":1829,"y":3128,"w":442,"h":447},
	"rotated": false,
	"trimmed": true,
	"spriteSourceSize": {"x":384,"y":105,"w":442,"h":447},
	"sourceSize": {"w":1200,"h":675}
},
"EscherStar3D.0012.png":
{
	"frame": {"x":1823,"y":2680,"w":430,"h":448},
	"rotated": false,
	"trimmed": true,
	"spriteSourceSize": {"x":389,"y":105,"w":430,"h":448},
	"sourceSize": {"w":1200,"h":675}
},
"EscherStar3D.0013.png":
{
	"frame": {"x":2297,"y":1342,"w":417,"h":449},
	"rotated": true,
	"trimmed": true,
	"spriteSourceSize": {"x":394,"y":105,"w":417,"h":449},
	"sourceSize": {"w":1200,"h":675}
},
"EscherStar3D.0014.png":
{
	"frame": {"x":3179,"y":2694,"w":401,"h":449},
	"rotated": true,
	"trimmed": true,
	"spriteSourceSize": {"x":402,"y":105,"w":401,"h":449},
	"sourceSize": {"w":1200,"h":675}
},
"EscherStar3D.0015.png":
{
	"frame": {"x":3646,"y":2246,"w":381,"h":450},
	"rotated": true,
	"trimmed": true,
	"spriteSourceSize": {"x":411,"y":105,"w":381,"h":450},
	"sourceSize": {"w":1200,"h":675}
},
"EscherStar3D.0016.png":
{
	"frame": {"x":3198,"y":1416,"w":357,"h":451},
	"rotated": true,
	"trimmed": true,
	"spriteSourceSize": {"x":423,"y":105,"w":357,"h":451},
	"sourceSize": {"w":1200,"h":675}
},
"EscherStar3D.0017.png":
{
	"frame": {"x":2285,"y":1905,"w":330,"h":451},
	"rotated": true,
	"trimmed": true,
	"spriteSourceSize": {"x":436,"y":105,"w":330,"h":451},
	"sourceSize": {"w":1200,"h":675}
},
"EscherStar3D.0018.png":
{
	"frame": {"x":2253,"y":2676,"w":298,"h":452},
	"rotated": false,
	"trimmed": true,
	"spriteSourceSize": {"x":452,"y":105,"w":298,"h":452},
	"sourceSize": {"w":1200,"h":675}
},
"EscherStar3D.0019.png":
{
	"frame": {"x":2275,"y":3557,"w":265,"h":452},
	"rotated": true,
	"trimmed": true,
	"spriteSourceSize": {"x":469,"y":105,"w":265,"h":452},
	"sourceSize": {"w":1200,"h":675}
},
"EscherStar3D.0020.png":
{
	"frame": {"x":3217,"y":448,"w":227,"h":453},
	"rotated": true,
	"trimmed": true,
	"spriteSourceSize": {"x":489,"y":105,"w":227,"h":453},
	"sourceSize": {"w":1200,"h":675}
},
"EscherStar3D.0021.png":
{
	"frame": {"x":1368,"y":3643,"w":189,"h":453},
	"rotated": true,
	"trimmed": true,
	"spriteSourceSize": {"x":510,"y":105,"w":189,"h":453},
	"sourceSize": {"w":1200,"h":675}
},
"EscherStar3D.0022.png":
{
	"frame": {"x":918,"y":3126,"w":161,"h":455},
	"rotated": true,
	"trimmed": true,
	"spriteSourceSize": {"x":532,"y":104,"w":161,"h":455},
	"sourceSize": {"w":1200,"h":675}
},
"EscherStar3D.0023.png":
{
	"frame": {"x":2291,"y":1759,"w":146,"h":455},
	"rotated": true,
	"trimmed": true,
	"spriteSourceSize": {"x":541,"y":104,"w":146,"h":455},
	"sourceSize": {"w":1200,"h":675}
},
"EscherStar3D.0024.png":
{
	"frame": {"x":2736,"y":2147,"w":131,"h":455},
	"rotated": true,
	"trimmed": true,
	"spriteSourceSize": {"x":549,"y":104,"w":131,"h":455},
	"sourceSize": {"w":1200,"h":675}
},
"EscherStar3D.0025.png":
{
	"frame": {"x":462,"y":3125,"w":133,"h":456},
	"rotated": true,
	"trimmed": true,
	"spriteSourceSize": {"x":554,"y":104,"w":133,"h":456},
	"sourceSize": {"w":1200,"h":675}
},
"EscherStar3D.0026.png":
{
	"frame": {"x":1851,"y":445,"w":150,"h":456},
	"rotated": true,
	"trimmed": true,
	"spriteSourceSize": {"x":545,"y":104,"w":150,"h":456},
	"sourceSize": {"w":1200,"h":675}
},
"EscherStar3D.0027.png":
{
	"frame": {"x":1373,"y":3128,"w":169,"h":456},
	"rotated": true,
	"trimmed": true,
	"spriteSourceSize": {"x":535,"y":104,"w":169,"h":456},
	"sourceSize": {"w":1200,"h":675}
},
"EscherStar3D.0028.png":
{
	"frame": {"x":2307,"y":446,"w":186,"h":455},
	"rotated": true,
	"trimmed": true,
	"spriteSourceSize": {"x":524,"y":104,"w":186,"h":455},
	"sourceSize": {"w":1200,"h":675}
},
"EscherStar3D.0029.png":
{
	"frame": {"x":2762,"y":448,"w":222,"h":455},
	"rotated": true,
	"trimmed": true,
	"spriteSourceSize": {"x":507,"y":104,"w":222,"h":455},
	"sourceSize": {"w":1200,"h":675}
},
"EscherStar3D.0030.png":
{
	"frame": {"x":0,"y":3573,"w":257,"h":454},
	"rotated": true,
	"trimmed": true,
	"spriteSourceSize": {"x":490,"y":104,"w":257,"h":454},
	"sourceSize": {"w":1200,"h":675}
},
"EscherStar3D.0031.png":
{
	"frame": {"x":914,"y":3287,"w":290,"h":454},
	"rotated": true,
	"trimmed": true,
	"spriteSourceSize": {"x":474,"y":104,"w":290,"h":454},
	"sourceSize": {"w":1200,"h":675}
},
"EscherStar3D.0032.png":
{
	"frame": {"x":461,"y":3258,"w":320,"h":453},
	"rotated": true,
	"trimmed": true,
	"spriteSourceSize": {"x":459,"y":104,"w":320,"h":453},
	"sourceSize": {"w":1200,"h":675}
},
"EscherStar3D.0033.png":
{
	"frame": {"x":1368,"y":3297,"w":346,"h":453},
	"rotated": true,
	"trimmed": true,
	"spriteSourceSize": {"x":446,"y":104,"w":346,"h":453},
	"sourceSize": {"w":1200,"h":675}
},
"EscherStar3D.0034.png":
{
	"frame": {"x":2746,"y":999,"w":369,"h":452},
	"rotated": true,
	"trimmed": true,
	"spriteSourceSize": {"x":434,"y":104,"w":369,"h":452},
	"sourceSize": {"w":1200,"h":675}
},
"EscherStar3D.0035.png":
{
	"frame": {"x":3210,"y":675,"w":387,"h":452},
	"rotated": true,
	"trimmed": true,
	"spriteSourceSize": {"x":424,"y":104,"w":387,"h":452},
	"sourceSize": {"w":1200,"h":675}
},
"EscherStar3D.0036.png":
{
	"frame": {"x":2746,"y":1743,"w":404,"h":451},
	"rotated": true,
	"trimmed": true,
	"spriteSourceSize": {"x":415,"y":104,"w":404,"h":451},
	"sourceSize": {"w":1200,"h":675}
},
"EscherStar3D.0037.png":
{
	"frame": {"x":3197,"y":1773,"w":417,"h":451},
	"rotated": true,
	"trimmed": true,
	"spriteSourceSize": {"x":408,"y":104,"w":417,"h":451},
	"sourceSize": {"w":1200,"h":675}
},
"EscherStar3D.0038.png":
{
	"frame": {"x":2281,"y":2235,"w":427,"h":450},
	"rotated": true,
	"trimmed": true,
	"spriteSourceSize": {"x":402,"y":104,"w":427,"h":450},
	"sourceSize": {"w":1200,"h":675}
},
"EscherStar3D.0039.png":
{
	"frame": {"x":3650,"y":1345,"w":437,"h":450},
	"rotated": false,
	"trimmed": true,
	"spriteSourceSize": {"x":397,"y":104,"w":437,"h":450},
	"sourceSize": {"w":1200,"h":675}
},
"EscherStar3D.0040.png":
{
	"frame": {"x":1842,"y":1345,"w":444,"h":449},
	"rotated": true,
	"trimmed": true,
	"spriteSourceSize": {"x":393,"y":104,"w":444,"h":449},
	"sourceSize": {"w":1200,"h":675}
},
"EscherStar3D.0041.png":
{
	"frame": {"x":1847,"y":896,"w":450,"h":449},
	"rotated": false,
	"trimmed": true,
	"spriteSourceSize": {"x":390,"y":104,"w":450,"h":449},
	"sourceSize": {"w":1200,"h":675}
},
"EscherStar3D.0042.png":
{
	"frame": {"x":1380,"y":2232,"w":454,"h":448},
	"rotated": false,
	"trimmed": true,
	"spriteSourceSize": {"x":387,"y":104,"w":454,"h":448},
	"sourceSize": {"w":1200,"h":675}
},
"EscherStar3D.0043.png":
{
	"frame": {"x":922,"y":1785,"w":458,"h":448},
	"rotated": false,
	"trimmed": true,
	"spriteSourceSize": {"x":384,"y":104,"w":458,"h":448},
	"sourceSize": {"w":1200,"h":675}
},
"EscherStar3D.0044.png":
{
	"frame": {"x":1383,"y":1338,"w":459,"h":447},
	"rotated": false,
	"trimmed": true,
	"spriteSourceSize": {"x":383,"y":104,"w":459,"h":447},
	"sourceSize": {"w":1200,"h":675}
},
"EscherStar3D.0045.png":
{
	"frame": {"x":923,"y":1338,"w":460,"h":447},
	"rotated": false,
	"trimmed": true,
	"spriteSourceSize": {"x":382,"y":104,"w":460,"h":447},
	"sourceSize": {"w":1200,"h":675}
},
"EscherStar3D.0046.png":
{
	"frame": {"x":462,"y":1338,"w":461,"h":447},
	"rotated": false,
	"trimmed": true,
	"spriteSourceSize": {"x":381,"y":104,"w":461,"h":447},
	"sourceSize": {"w":1200,"h":675}
},
"EscherStar3D.0047.png":
{
	"frame": {"x":0,"y":892,"w":462,"h":447},
	"rotated": false,
	"trimmed": true,
	"spriteSourceSize": {"x":380,"y":104,"w":462,"h":447},
	"sourceSize": {"w":1200,"h":675}
},
"EscherStar3D.0048.png":
{
	"frame": {"x":0,"y":1339,"w":462,"h":447},
	"rotated": false,
	"trimmed": true,
	"spriteSourceSize": {"x":380,"y":104,"w":462,"h":447},
	"sourceSize": {"w":1200,"h":675}
},
"EscherStar3D.0049.png":
{
	"frame": {"x":0,"y":1786,"w":462,"h":447},
	"rotated": false,
	"trimmed": true,
	"spriteSourceSize": {"x":380,"y":104,"w":462,"h":447},
	"sourceSize": {"w":1200,"h":675}
},
"EscherStar3D.0050.png":
{
	"frame": {"x":0,"y":2233,"w":462,"h":447},
	"rotated": false,
	"trimmed": true,
	"spriteSourceSize": {"x":380,"y":104,"w":462,"h":447},
	"sourceSize": {"w":1200,"h":675}
},
"EscherStar3D.0051.png":
{
	"frame": {"x":463,"y":446,"w":463,"h":446},
	"rotated": false,
	"trimmed": true,
	"spriteSourceSize": {"x":379,"y":104,"w":463,"h":446},
	"sourceSize": {"w":1200,"h":675}
},
"EscherStar3D.0052.png":
{
	"frame": {"x":1389,"y":0,"w":462,"h":446},
	"rotated": false,
	"trimmed": true,
	"spriteSourceSize": {"x":379,"y":104,"w":462,"h":446},
	"sourceSize": {"w":1200,"h":675}
},
"EscherStar3D.0053.png":
{
	"frame": {"x":926,"y":0,"w":463,"h":446},
	"rotated": false,
	"trimmed": true,
	"spriteSourceSize": {"x":378,"y":104,"w":463,"h":446},
	"sourceSize": {"w":1200,"h":675}
},
"EscherStar3D.0054.png":
{
	"frame": {"x":1851,"y":0,"w":462,"h":445},
	"rotated": false,
	"trimmed": true,
	"spriteSourceSize": {"x":378,"y":104,"w":462,"h":445},
	"sourceSize": {"w":1200,"h":675}
},
"EscherStar3D.0055.png":
{
	"frame": {"x":462,"y":2679,"w":460,"h":446},
	"rotated": false,
	"trimmed": true,
	"spriteSourceSize": {"x":378,"y":104,"w":460,"h":446},
	"sourceSize": {"w":1200,"h":675}
},
"EscherStar3D.0056.png":
{
	"frame": {"x":2313,"y":0,"w":456,"h":446},
	"rotated": false,
	"trimmed": true,
	"spriteSourceSize": {"x":379,"y":104,"w":456,"h":446},
	"sourceSize": {"w":1200,"h":675}
},
"EscherStar3D.0057.png":
{
	"frame": {"x":922,"y":2680,"w":451,"h":446},
	"rotated": false,
	"trimmed": true,
	"spriteSourceSize": {"x":381,"y":105,"w":451,"h":446},
	"sourceSize": {"w":1200,"h":675}
},
"EscherStar3D.0058.png":
{
	"frame": {"x":1834,"y":2234,"w":442,"h":447},
	"rotated": true,
	"trimmed": true,
	"spriteSourceSize": {"x":384,"y":105,"w":442,"h":447},
	"sourceSize": {"w":1200,"h":675}
},
"EscherStar3D.0059.png":
{
	"frame": {"x":3662,"y":898,"w":433,"h":447},
	"rotated": false,
	"trimmed": true,
	"spriteSourceSize": {"x":388,"y":105,"w":433,"h":447},
	"sourceSize": {"w":1200,"h":675}
},
"EscherStar3D.0060.png":
{
	"frame": {"x":3674,"y":0,"w":420,"h":448},
	"rotated": false,
	"trimmed": true,
	"spriteSourceSize": {"x":393,"y":105,"w":420,"h":448},
	"sourceSize": {"w":1200,"h":675}
},
"EscherStar3D.0061.png":
{
	"frame": {"x":2730,"y":2671,"w":405,"h":449},
	"rotated": true,
	"trimmed": true,
	"spriteSourceSize": {"x":400,"y":105,"w":405,"h":449},
	"sourceSize": {"w":1200,"h":675}
},
"EscherStar3D.0062.png":
{
	"frame": {"x":2730,"y":3076,"w":387,"h":449},
	"rotated": true,
	"trimmed": true,
	"spriteSourceSize": {"x":408,"y":105,"w":387,"h":449},
	"sourceSize": {"w":1200,"h":675}
},
"EscherStar3D.0063.png":
{
	"frame": {"x":3182,"y":2330,"w":364,"h":450},
	"rotated": true,
	"trimmed": true,
	"spriteSourceSize": {"x":419,"y":105,"w":364,"h":450},
	"sourceSize": {"w":1200,"h":675}
},
"EscherStar3D.0064.png":
{
	"frame": {"x":3179,"y":3095,"w":338,"h":451},
	"rotated": true,
	"trimmed": true,
	"spriteSourceSize": {"x":432,"y":105,"w":338,"h":451},
	"sourceSize": {"w":1200,"h":675}
},
"EscherStar3D.0065.png":
{
	"frame": {"x":2727,"y":3463,"w":309,"h":451},
	"rotated": true,
	"trimmed": true,
	"spriteSourceSize": {"x":447,"y":105,"w":309,"h":451},
	"sourceSize": {"w":1200,"h":675}
},
"EscherStar3D.0066.png":
{
	"frame": {"x":3628,"y":2752,"w":277,"h":451},
	"rotated": true,
	"trimmed": true,
	"spriteSourceSize": {"x":463,"y":105,"w":277,"h":451},
	"sourceSize": {"w":1200,"h":675}
},
"EscherStar3D.0067.png":
{
	"frame": {"x":454,"y":3578,"w":242,"h":452},
	"rotated": true,
	"trimmed": true,
	"spriteSourceSize": {"x":481,"y":105,"w":242,"h":452},
	"sourceSize": {"w":1200,"h":675}
},
"EscherStar3D.0068.png":
{
	"frame": {"x":3630,"y":3235,"w":204,"h":453},
	"rotated": true,
	"trimmed": true,
	"spriteSourceSize": {"x":501,"y":105,"w":204,"h":453},
	"sourceSize": {"w":1200,"h":675}
},
"EscherStar3D.0069.png":
{
	"frame": {"x":3178,"y":3463,"w":167,"h":453},
	"rotated": true,
	"trimmed": true,
	"spriteSourceSize": {"x":521,"y":105,"w":167,"h":453},
	"sourceSize": {"w":1200,"h":675}
},
"EscherStar3D.0070.png":
{
	"frame": {"x":914,"y":3577,"w":153,"h":454},
	"rotated": true,
	"trimmed": true,
	"spriteSourceSize": {"x":527,"y":104,"w":153,"h":454},
	"sourceSize": {"w":1200,"h":675}
},
"EscherStar3D.0071.png":
{
	"frame": {"x":3191,"y":2190,"w":140,"h":455},
	"rotated": true,
	"trimmed": true,
	"spriteSourceSize": {"x":533,"y":104,"w":140,"h":455},
	"sourceSize": {"w":1200,"h":675}
},
"EscherStar3D.0072.png":
{
	"frame": {"x":3632,"y":2627,"w":125,"h":455},
	"rotated": true,
	"trimmed": true,
	"spriteSourceSize": {"x":541,"y":104,"w":125,"h":455},
	"sourceSize": {"w":1200,"h":675}
},
"EscherStar3D.0073.png":
{
	"frame": {"x":3631,"y":3439,"w":141,"h":455},
	"rotated": true,
	"trimmed": true,
	"spriteSourceSize": {"x":534,"y":104,"w":141,"h":455},
	"sourceSize": {"w":1200,"h":675}
},
"EscherStar3D.0074.png":
{
	"frame": {"x":3178,"y":3630,"w":160,"h":455},
	"rotated": true,
	"trimmed": true,
	"spriteSourceSize": {"x":526,"y":104,"w":160,"h":455},
	"sourceSize": {"w":1200,"h":675}
},
"EscherStar3D.0075.png":
{
	"frame": {"x":2551,"y":2662,"w":179,"h":455},
	"rotated": false,
	"trimmed": true,
	"spriteSourceSize": {"x":519,"y":104,"w":179,"h":455},
	"sourceSize": {"w":1200,"h":675}
},
"EscherStar3D.0076.png":
{
	"frame": {"x":3630,"y":3029,"w":206,"h":454},
	"rotated": true,
	"trimmed": true,
	"spriteSourceSize": {"x":512,"y":104,"w":206,"h":454},
	"sourceSize": {"w":1200,"h":675}
},
"EscherStar3D.0077.png":
{
	"frame": {"x":1821,"y":3575,"w":236,"h":454},
	"rotated": true,
	"trimmed": true,
	"spriteSourceSize": {"x":500,"y":104,"w":236,"h":454},
	"sourceSize": {"w":1200,"h":675}
},
"EscherStar3D.0078.png":
{
	"frame": {"x":2303,"y":632,"w":271,"h":454},
	"rotated": true,
	"trimmed": true,
	"spriteSourceSize": {"x":483,"y":104,"w":271,"h":454},
	"sourceSize": {"w":1200,"h":675}
},
"EscherStar3D.0079.png":
{
	"frame": {"x":1850,"y":595,"w":301,"h":453},
	"rotated": true,
	"trimmed": true,
	"spriteSourceSize": {"x":468,"y":104,"w":301,"h":453},
	"sourceSize": {"w":1200,"h":675}
},
"EscherStar3D.0080.png":
{
	"frame": {"x":2757,"y":670,"w":329,"h":453},
	"rotated": true,
	"trimmed": true,
	"spriteSourceSize": {"x":454,"y":104,"w":329,"h":453},
	"sourceSize": {"w":1200,"h":675}
},
"EscherStar3D.0081.png":
{
	"frame": {"x":3198,"y":1062,"w":354,"h":452},
	"rotated": true,
	"trimmed": true,
	"spriteSourceSize": {"x":442,"y":104,"w":354,"h":452},
	"sourceSize": {"w":1200,"h":675}
},
"EscherStar3D.0082.png":
{
	"frame": {"x":2746,"y":1368,"w":375,"h":452},
	"rotated": true,
	"trimmed": true,
	"spriteSourceSize": {"x":431,"y":104,"w":375,"h":452},
	"sourceSize": {"w":1200,"h":675}
},
"EscherStar3D.0083.png":
{
	"frame": {"x":2731,"y":2278,"w":393,"h":451},
	"rotated": true,
	"trimmed": true,
	"spriteSourceSize": {"x":421,"y":104,"w":393,"h":451},
	"sourceSize": {"w":1200,"h":675}
},
"EscherStar3D.0084.png":
{
	"frame": {"x":3648,"y":1795,"w":408,"h":451},
	"rotated": false,
	"trimmed": true,
	"spriteSourceSize": {"x":413,"y":104,"w":408,"h":451},
	"sourceSize": {"w":1200,"h":675}
},
"EscherStar3D.0085.png":
{
	"frame": {"x":3670,"y":448,"w":420,"h":450},
	"rotated": false,
	"trimmed": true,
	"spriteSourceSize": {"x":406,"y":104,"w":420,"h":450},
	"sourceSize": {"w":1200,"h":675}
},
"EscherStar3D.0086.png":
{
	"frame": {"x":2271,"y":3128,"w":429,"h":450},
	"rotated": true,
	"trimmed": true,
	"spriteSourceSize": {"x":401,"y":104,"w":429,"h":450},
	"sourceSize": {"w":1200,"h":675}
},
"EscherStar3D.0087.png":
{
	"frame": {"x":2297,"y":903,"w":439,"h":449},
	"rotated": true,
	"trimmed": true,
	"spriteSourceSize": {"x":396,"y":104,"w":439,"h":449},
	"sourceSize": {"w":1200,"h":675}
},
"EscherStar3D.0088.png":
{
	"frame": {"x":1836,"y":1789,"w":445,"h":449},
	"rotated": true,
	"trimmed": true,
	"spriteSourceSize": {"x":393,"y":104,"w":445,"h":449},
	"sourceSize": {"w":1200,"h":675}
},
"EscherStar3D.0089.png":
{
	"frame": {"x":3223,"y":0,"w":451,"h":448},
	"rotated": false,
	"trimmed": true,
	"spriteSourceSize": {"x":389,"y":104,"w":451,"h":448},
	"sourceSize": {"w":1200,"h":675}
},
"EscherStar3D.0090.png":
{
	"frame": {"x":2769,"y":0,"w":454,"h":448},
	"rotated": false,
	"trimmed": true,
	"spriteSourceSize": {"x":387,"y":104,"w":454,"h":448},
	"sourceSize": {"w":1200,"h":675}
},
"EscherStar3D.0091.png":
{
	"frame": {"x":922,"y":2233,"w":458,"h":447},
	"rotated": false,
	"trimmed": true,
	"spriteSourceSize": {"x":384,"y":104,"w":458,"h":447},
	"sourceSize": {"w":1200,"h":675}
},
"EscherStar3D.0092.png":
{
	"frame": {"x":462,"y":2232,"w":460,"h":447},
	"rotated": false,
	"trimmed": true,
	"spriteSourceSize": {"x":382,"y":104,"w":460,"h":447},
	"sourceSize": {"w":1200,"h":675}
},
"EscherStar3D.0093.png":
{
	"frame": {"x":0,"y":3126,"w":461,"h":447},
	"rotated": false,
	"trimmed": true,
	"spriteSourceSize": {"x":381,"y":104,"w":461,"h":447},
	"sourceSize": {"w":1200,"h":675}
},
"EscherStar3D.0094.png":
{
	"frame": {"x":1386,"y":892,"w":461,"h":446},
	"rotated": false,
	"trimmed": true,
	"spriteSourceSize": {"x":381,"y":104,"w":461,"h":446},
	"sourceSize": {"w":1200,"h":675}
},
"EscherStar3D.0095.png":
{
	"frame": {"x":924,"y":892,"w":462,"h":446},
	"rotated": false,
	"trimmed": true,
	"spriteSourceSize": {"x":380,"y":104,"w":462,"h":446},
	"sourceSize": {"w":1200,"h":675}
},
"EscherStar3D.0096.png":
{
	"frame": {"x":1388,"y":446,"w":462,"h":446},
	"rotated": false,
	"trimmed": true,
	"spriteSourceSize": {"x":380,"y":104,"w":462,"h":446},
	"sourceSize": {"w":1200,"h":675}
}},
"animations": {
	"EscherStar3D.": ["EscherStar3D.0001.png","EscherStar3D.0003.png","EscherStar3D.0004.png","EscherStar3D.0005.png","EscherStar3D.0006.png","EscherStar3D.0007.png","EscherStar3D.0008.png","EscherStar3D.0009.png","EscherStar3D.0010.png","EscherStar3D.0011.png","EscherStar3D.0012.png","EscherStar3D.0013.png","EscherStar3D.0014.png","EscherStar3D.0015.png","EscherStar3D.0016.png","EscherStar3D.0017.png","EscherStar3D.0018.png","EscherStar3D.0019.png","EscherStar3D.0020.png","EscherStar3D.0021.png","EscherStar3D.0022.png","EscherStar3D.0023.png","EscherStar3D.0024.png","EscherStar3D.0025.png","EscherStar3D.0026.png","EscherStar3D.0027.png","EscherStar3D.0028.png","EscherStar3D.0029.png","EscherStar3D.0030.png","EscherStar3D.0031.png","EscherStar3D.0032.png","EscherStar3D.0033.png","EscherStar3D.0034.png","EscherStar3D.0035.png","EscherStar3D.0036.png","EscherStar3D.0037.png","EscherStar3D.0038.png","EscherStar3D.0039.png","EscherStar3D.0040.png","EscherStar3D.0041.png","EscherStar3D.0042.png","EscherStar3D.0043.png","EscherStar3D.0044.png","EscherStar3D.0045.png","EscherStar3D.0046.png","EscherStar3D.0047.png","EscherStar3D.0048.png","EscherStar3D.0049.png","EscherStar3D.0050.png","EscherStar3D.0051.png","EscherStar3D.0052.png","EscherStar3D.0053.png","EscherStar3D.0054.png","EscherStar3D.0055.png","EscherStar3D.0056.png","EscherStar3D.0057.png","EscherStar3D.0058.png","EscherStar3D.0059.png","EscherStar3D.0060.png","EscherStar3D.0061.png","EscherStar3D.0062.png","EscherStar3D.0063.png","EscherStar3D.0064.png","EscherStar3D.0065.png","EscherStar3D.0066.png","EscherStar3D.0067.png","EscherStar3D.0068.png","EscherStar3D.0069.png","EscherStar3D.0070.png","EscherStar3D.0071.png","EscherStar3D.0072.png","EscherStar3D.0073.png","EscherStar3D.0074.png","EscherStar3D.0075.png","EscherStar3D.0076.png","EscherStar3D.0077.png","EscherStar3D.0078.png","EscherStar3D.0079.png","EscherStar3D.0080.png","EscherStar3D.0081.png","EscherStar3D.0082.png","EscherStar3D.0083.png","EscherStar3D.0084.png","EscherStar3D.0085.png","EscherStar3D.0086.png","EscherStar3D.0087.png","EscherStar3D.0088.png","EscherStar3D.0089.png","EscherStar3D.0090.png","EscherStar3D.0091.png","EscherStar3D.0092.png","EscherStar3D.0093.png","EscherStar3D.0094.png","EscherStar3D.0095.png","EscherStar3D.0096.png"]
},
"meta": {
	"app": "https://www.codeandweb.com/texturepacker",
	"version": "1.0",
	"image": "EscherStar3D.png",
	"format": "RGBA8888",
	"size": {"w":4096,"h":3832},
	"scale": "0.9375",
	"smartupdate": "$TexturePacker:SmartUpdate:721d577bf52317bed314b857299b5a1f:ebc50fd46f8c03dfd0b720d627c0a846:24ba81cb314e3b022c9cc1574cd1926a$"
}
}
